asyncpg-stubs/__init__.pyi
asyncpg-stubs/_asyncio_compat.pyi
asyncpg-stubs/_testbase/__init__.pyi
asyncpg-stubs/_testbase/fuzzer.pyi
asyncpg-stubs/_version.pyi
asyncpg-stubs/cluster.pyi
asyncpg-stubs/compat.pyi
asyncpg-stubs/connect_utils.pyi
asyncpg-stubs/connection.pyi
asyncpg-stubs/connresource.pyi
asyncpg-stubs/cursor.pyi
asyncpg-stubs/exceptions/__init__.pyi
asyncpg-stubs/exceptions/_base.pyi
asyncpg-stubs/introspection.pyi
asyncpg-stubs/pgproto/__init__.pyi
asyncpg-stubs/pgproto/pgproto.pyi
asyncpg-stubs/pgproto/types.pyi
asyncpg-stubs/pool.pyi
asyncpg-stubs/prepared_stmt.pyi
asyncpg-stubs/protocol/__init__.pyi
asyncpg-stubs/protocol/codecs/__init__.pyi
asyncpg-stubs/protocol/protocol.pyi
asyncpg-stubs/serverversion.pyi
asyncpg-stubs/transaction.pyi
asyncpg-stubs/types.pyi
asyncpg-stubs/utils.pyi
asyncpg_stubs-0.30.2.dist-info/LICENSE
asyncpg_stubs-0.30.2.dist-info/METADATA
asyncpg_stubs-0.30.2.dist-info/WHEEL
asyncpg_stubs-0.30.2.dist-info/RECORD
